{
  "ComponentIndexes": {},
  "ControlUniqueIds": {
    "Add Order Screen": 47,
    "Add Server Screen": 70,
    "App": 1,
    "BackIcon1_1": 12,
    "BackIcon1_2": 95,
    "BackIcon1_3": 121,
    "Billing Screen": 90,
    "btnAddItem": 52,
    "btnCreateNewOrder": 48,
    "btnEditOrderItem": 43,
    "btnLogin": 10,
    "btnLogout": 119,
    "btnLookupServerID": 16,
    "btnNewServerBackArrow": 71,
    "btnPay": 41,
    "btnPlaceOrder": 69,
    "btnSubmitMenuItemChange": 139,
    "btnSubmitNewServer": 89,
    "btnSubmitServerChange": 113,
    "CreateOrderForm": 57,
    "Customization Request_DataCard1": 151,
    "DataCardKey13": 60,
    "DataCardValue13": 61,
    "drpNewServerTeamLead": 87,
    "drpTeamLead": 111,
    "Edit Order Item Screen": 120,
    "Edit Server Screen": 94,
    "ErrorMessage1": 78,
    "ErrorMessage2": 83,
    "ErrorMessage3": 102,
    "ErrorMessage4": 107,
    "ErrorMessage5": 88,
    "ErrorMessage6": 112,
    "ErrorMessage7": 149,
    "ErrorMessage8": 154,
    "ErrorMessage9": 62,
    "frmEditOrderItem": 123,
    "frmEditServer": 97,
    "frmNewServer": 73,
    "Full Name_DataCard1": 74,
    "Full Name_DataCard2": 98,
    "Gallery1": 156,
    "Gallery4": 49,
    "Gallery5": 63,
    "galleryTemplate1": 40,
    "galleryTemplate2": 25,
    "galleryTemplate3": 157,
    "galleryTemplate6": 50,
    "galleryTemplate7": 64,
    "icnBack": 23,
    "icnCheck1": 32,
    "icnCircle1": 31,
    "icnCreateOrder": 37,
    "icnCreateServer": 22,
    "icnOrderListBack": 38,
    "Icon1": 92,
    "imgSeth'sBrewery": 179,
    "Label4": 91,
    "lblAddServerPin": 81,
    "lblCustomizationRequest": 152,
    "lblEditFullName": 100,
    "lblForgotYourID": 7,
    "lblFullName": 14,
    "lblGreetingMessage": 116,
    "lblItemName": 51,
    "lblMenuItem": 147,
    "lblModifyServers": 118,
    "lblNewServerFullName": 76,
    "lblNewServerTeamLead": 86,
    "lblOrderCart": 56,
    "lblOrderNumber": 42,
    "lblPINText": 8,
    "lblPrice": 53,
    "lblRestaurantTitle": 4,
    "lblRestaurantTitle_1": 115,
    "lblRestaurantTitle_2": 13,
    "lblServerIDFound": 18,
    "lblServerIDText": 5,
    "lblServerLIstServerID": 28,
    "lblServerListServerName": 26,
    "lblServerPin": 105,
    "lblServersListScreenTitle": 21,
    "lblSubtotal": 68,
    "lblSuccessMsg1": 33,
    "lblTeamLead": 110,
    "lblViewYourOrders": 117,
    "lblYourServerID": 17,
    "Logged In Landing Page Screen": 114,
    "Login Screen": 3,
    "Lookup Server ID by Full Name Screen": 11,
    "Menu Item_DataCard1": 146,
    "NextArrow11": 65,
    "NextArrow3": 27,
    "NextArrow6": 177,
    "Orders List Screen": 34,
    "OrdersListGallery": 39,
    "PIN_DataCard1": 79,
    "PIN_DataCard2": 103,
    "Rectangle1": 55,
    "Rectangle2": 93,
    "RectQuickActionBar1": 35,
    "RectQuickActionBar1_1": 46,
    "RectQuickActionBar2": 20,
    "Separator1": 44,
    "Separator11": 67,
    "Separator3": 29,
    "Separator7": 178,
    "Separator9": 54,
    "Server ID_DataCard4": 58,
    "Servers List Screen": 19,
    "ServersListGallery": 24,
    "StarVisible1": 75,
    "StarVisible2": 80,
    "StarVisible3": 99,
    "StarVisible4": 104,
    "StarVisible5": 85,
    "StarVisible6": 109,
    "StarVisible7": 150,
    "StarVisible8": 155,
    "StarVisible9": 59,
    "Subtitle4": 176,
    "Success Screen": 30,
    "Team Lead_DataCard1": 84,
    "Team Lead_DataCard2": 108,
    "Title10": 66,
    "Title6": 175,
    "txtAddServerPin": 82,
    "txtCreateNewServerLabel": 72,
    "txtCustomizationRequest": 153,
    "txtEditFullName": 101,
    "txtEditMenuItemLabel": 122,
    "txtEditServerLabel": 96,
    "txtEnterFullName": 15,
    "txtMenuItem": 148,
    "txtNewServerFullName": 77,
    "txtOrdersListGalleryTitle": 36,
    "txtPIN": 9,
    "txtServerID": 6,
    "txtServerPin": 106
  },
  "FunctionParamsInvariantScripts": {},
  "FunctionParamsInvariantScriptsOnInstances": {},
  "HeaderLastSavedDateTimeUTC": "06/15/2022 00:29:13",
  "IsLegacyComponentAllowGlobalScopeCase": false,
  "LocalConnectionIDReferences": {},
  "LocalDatabaseReferencesAsEmpty": false,
  "LocalResourceFileNames": {
    "SethsBrewery": "6d4d9831-ed11-4132-a439-a9dde8f3c122.png"
  },
  "LocalResourceRootPaths": {
    "SethsBrewery": "https://docserverpwaprodwus.blob.core.windows.net/e9b6958f-304d-43b3-8240-c04dedb21e13-1/resource/54974aa6-5de9-4533-b4da-fde8317bf209.png?sv=2017-04-17&sr=b&sig=9njqA9SpmWomQ6axrm%2BvyFgfRwM4w%2Bw4GI3hdbngFu8%3D&spr=https&se=2022-06-16T00%3A18%3A43Z&sp=r"
  },
  "OrderComponentMetadata": {},
  "OrderComponentTemplate": {},
  "OrderDataSource": {
    "ComboBoxSample": 17,
    "CustomGallerySample": 18,
    "Menus": 19,
    "Menus\\cre49_menu_statecode": 1,
    "Menus\\cre49_menu_statuscode": 2,
    "Menus\\cre49_menucategories": 0,
    "Menus\\default.cds_cre49_menu_views": 13,
    "Order Details": 20,
    "Order Details\\default.cds_kitchen_orderdetail_views": 14,
    "Order Details\\kitchen_kitchenmodificationstatus": 3,
    "Order Details\\kitchen_orderdetail_statecode": 5,
    "Order Details\\kitchen_orderdetail_statuscode": 6,
    "Order Details\\kitchen_pendingyesno": 4,
    "orderCart": 23,
    "OrderingStaff": 21,
    "OrderingStaff\\default.cds_order_orderingstaff_views": 15,
    "OrderingStaff\\kitchen_order_orderingstaff_kitchen_teamlead": 7,
    "OrderingStaff\\order_orderingstaff_statecode": 8,
    "OrderingStaff\\order_orderingstaff_statuscode": 9,
    "Orders": 22,
    "Orders\\default.cds_kitchen_order_views": 16,
    "Orders\\kitchen_order_statecode": 11,
    "Orders\\kitchen_order_statuscode": 12,
    "Orders\\kitchen_orderstatus": 10
  },
  "OrderGroupControls": {},
  "OrderPcfTemplate": {},
  "OrderTemplate": {},
  "OrderXMLTemplate": {
    "button": 3,
    "circle": 7,
    "combobox": 9,
    "form": 8,
    "gallery": 6,
    "icon": 4,
    "image": 1,
    "label": 0,
    "rectangle": 5,
    "text": 2
  },
  "PublishOrderIndices": {
    "Add Order Screen": 1,
    "Add Server Screen": 24,
    "App": 0,
    "BackIcon1_1": 8,
    "BackIcon1_2": 49,
    "BackIcon1_3": 80,
    "Billing Screen": 45,
    "btnAddItem": 103,
    "btnCreateNewOrder": 99,
    "btnEditOrderItem": 76,
    "btnLogin": 7,
    "btnLogout": 19,
    "btnLookupServerID": 12,
    "btnNewServerBackArrow": 30,
    "btnPay": 74,
    "btnPlaceOrder": 120,
    "btnSubmitMenuItemChange": 98,
    "btnSubmitNewServer": 48,
    "btnSubmitServerChange": 67,
    "CreateOrderForm": 108,
    "Customization Request_DataCard1": 93,
    "DataCardKey13": 111,
    "DataCardValue13": 112,
    "drpNewServerTeamLead": 46,
    "drpTeamLead": 65,
    "Edit Order Item Screen": 49,
    "Edit Server Screen": 49,
    "ErrorMessage1": 37,
    "ErrorMessage2": 42,
    "ErrorMessage3": 56,
    "ErrorMessage4": 61,
    "ErrorMessage5": 47,
    "ErrorMessage6": 66,
    "ErrorMessage7": 92,
    "ErrorMessage8": 97,
    "ErrorMessage9": 113,
    "frmEditOrderItem": 87,
    "frmEditServer": 51,
    "frmNewServer": 32,
    "Full Name_DataCard1": 33,
    "Full Name_DataCard2": 52,
    "Gallery1": 81,
    "Gallery4": 100,
    "Gallery5": 114,
    "galleryTemplate1": 73,
    "galleryTemplate2": 25,
    "galleryTemplate3": 82,
    "galleryTemplate6": 101,
    "galleryTemplate7": 115,
    "icnBack": 23,
    "icnCheck1": 122,
    "icnCircle1": 121,
    "icnCreateOrder": 70,
    "icnCreateServer": 22,
    "icnOrderListBack": 71,
    "Icon1": 125,
    "imgSeth'sBrewery": 1,
    "Label4": 124,
    "lblAddServerPin": 40,
    "lblCustomizationRequest": 95,
    "lblEditFullName": 54,
    "lblForgotYourID": 4,
    "lblFullName": 10,
    "lblGreetingMessage": 16,
    "lblItemName": 102,
    "lblMenuItem": 90,
    "lblModifyServers": 18,
    "lblNewServerFullName": 35,
    "lblNewServerTeamLead": 45,
    "lblOrderCart": 107,
    "lblOrderNumber": 75,
    "lblPINText": 5,
    "lblPrice": 104,
    "lblRestaurantTitle": 0,
    "lblRestaurantTitle_1": 15,
    "lblRestaurantTitle_2": 9,
    "lblServerIDFound": 14,
    "lblServerIDText": 2,
    "lblServerLIstServerID": 28,
    "lblServerListServerName": 26,
    "lblServerPin": 59,
    "lblServersListScreenTitle": 21,
    "lblSubtotal": 119,
    "lblSuccessMsg1": 123,
    "lblTeamLead": 64,
    "lblViewYourOrders": 17,
    "lblYourServerID": 13,
    "Logged In Landing Page Screen": 69,
    "Login Screen": 75,
    "Lookup Server ID by Full Name Screen": 83,
    "Menu Item_DataCard1": 88,
    "NextArrow11": 116,
    "NextArrow3": 27,
    "NextArrow6": 84,
    "Orders List Screen": 91,
    "OrdersListGallery": 72,
    "PIN_DataCard1": 38,
    "PIN_DataCard2": 57,
    "Rectangle1": 106,
    "Rectangle2": 126,
    "RectQuickActionBar1": 68,
    "RectQuickActionBar1_1": 78,
    "RectQuickActionBar2": 20,
    "Separator1": 77,
    "Separator11": 118,
    "Separator3": 29,
    "Separator7": 86,
    "Separator9": 105,
    "Server ID_DataCard4": 109,
    "Servers List Screen": 104,
    "ServersListGallery": 24,
    "StarVisible1": 34,
    "StarVisible2": 39,
    "StarVisible3": 53,
    "StarVisible4": 58,
    "StarVisible5": 44,
    "StarVisible6": 63,
    "StarVisible7": 89,
    "StarVisible8": 94,
    "StarVisible9": 110,
    "Subtitle4": 85,
    "Success Screen": 115,
    "Team Lead_DataCard1": 43,
    "Team Lead_DataCard2": 62,
    "Title10": 117,
    "Title6": 83,
    "txtAddServerPin": 41,
    "txtCreateNewServerLabel": 31,
    "txtCustomizationRequest": 96,
    "txtEditFullName": 55,
    "txtEditMenuItemLabel": 79,
    "txtEditServerLabel": 50,
    "txtEnterFullName": 11,
    "txtMenuItem": 91,
    "txtNewServerFullName": 36,
    "txtOrdersListGalleryTitle": 69,
    "txtPIN": 6,
    "txtServerID": 3,
    "txtServerPin": 60
  },
  "ResourcesJsonIndices": {
    "Image-SampleImage": 0,
    "Image-SethsBrewery": 1
  },
  "RuleScreenIdWithoutScreen": {},
  "TemplateVersions": {},
  "VolatileProperties": {
    "AnalysisLoadTime": 0.9991323,
    "ControlCount": {
      "button": 11,
      "circle": 1,
      "combobox": 3,
      "form": 4,
      "gallery": 4,
      "galleryTemplate": 4,
      "icon": 13,
      "label": 57,
      "rectangle": 9,
      "screen": 11,
      "text": 10,
      "typedDataCard": 10
    },
    "DeserializationLoadTime": 2.440799,
    "ErrorCount": 1
  },
  "WasLocalDatabaseReferencesEmpty": false
}